lowhaio_retry.py
lowhaio_retry-0.0.5.dist-info/LICENSE
lowhaio_retry-0.0.5.dist-info/METADATA
lowhaio_retry-0.0.5.dist-info/WHEEL
lowhaio_retry-0.0.5.dist-info/top_level.txt
lowhaio_retry-0.0.5.dist-info/RECORD
