Metadata-Version: 2.1
Name: lowhaio-retry
Version: 0.0.5
Summary: Wrapper that retries failed lowhaio HTTP requests
Home-page: https://github.com/michalc/lowhaio-retry
Author: Michal Charemza
Author-email: michal@charemza.name
License: UNKNOWN
Platform: UNKNOWN
Classifier: Programming Language :: Python :: 3
Classifier: License :: OSI Approved :: MIT License
Classifier: Operating System :: OS Independent
Classifier: Framework :: AsyncIO
Requires-Python: >=3.6.3
